<?xml version="1.0" encoding="utf-8"?>
<!--
- phpMyAdmin XML Dump
- version 4.0.10.14
- http://www.phpmyadmin.net
-
- Host: localhost
- Generation Time: Mar 01, 2016 at 10:12 PM
- Server version: 5.5.48
- PHP Version: 5.5.32
-->
<pma_xml_export version="1.0" xmlns:pma="http://www.phpmyadmin.net/some_doc_url/">
	<!--
    - Structure schemas
    -->
	<pma:structure_schemas>
		<pma:database name="neogame" collation="latin1_swedish_ci" charset="latin1">
			<pma:table name="recipes">
                CREATE TABLE `recipes` (
                  `nID` int(3) NOT NULL AUTO_INCREMENT,
                  `strName` varchar(255) NOT NULL,
                  `strSecretName` varchar(255) NOT NULL,
                  `strTools` varchar(255) NOT NULL DEFAULT '',
                  `strConsumed` varchar(255) NOT NULL DEFAULT '',
                  `strDestroyed` varchar(255) NOT NULL DEFAULT '',
                  `nTreasureID` int(4) NOT NULL DEFAULT '3',
                  `fHours` float NOT NULL DEFAULT '0',
                  `nReverse` int(2) NOT NULL DEFAULT '0',
                  `nHiddenID` tinyint(1) NOT NULL DEFAULT '0',
                  `bIdentify` tinyint(1) NOT NULL DEFAULT '0',
                  `bTransferComponents` tinyint(1) NOT NULL DEFAULT '0',
                  `vAlsoTry` varchar(255) NOT NULL,
                  `nTempTreasureID` int(4) NOT NULL DEFAULT '3',
                  `bDegradeOutput` tinyint(1) NOT NULL DEFAULT '1',
                  `strType` varchar(255) NOT NULL,
                  `bScrap` tinyint(1) NOT NULL DEFAULT '1',
                  PRIMARY KEY (`nID`)
                ) ENGINE=InnoDB AUTO_INCREMENT=106 DEFAULT CHARSET=latin1;
            </pma:table>
		</pma:database>
	</pma:structure_schemas>
	<!--
    - Database: 'neogame'
    -->
	<database name="neogame">
		<!-- Table recipes -->
		<table name="recipes">
			<column name="nID">1</column>
			<column name="strName">fogueira media (acesa)</column>
			<column name="strSecretName"></column>
			<column name="strTools">1x1</column>
			<column name="strConsumed">1x2+1x3</column>
			<column name="strDestroyed"></column>
			<column name="nTreasureID">8</column>
			<column name="fHours">0.25</column>
			<column name="nReverse">0</column>
			<column name="nHiddenID">0</column>
			<column name="bIdentify">0</column>
			<column name="bTransferComponents">0</column>
			<column name="vAlsoTry"></column>
			<column name="nTempTreasureID">3</column>
			<column name="bDegradeOutput">0</column>
			<column name="strType">tool</column>
			<column name="bScrap">1</column>
		</table>
		<table name="recipes">
			<column name="nID">2</column>
			<column name="strName">fogueira pequena (acesa)</column>
			<column name="strSecretName"></column>
			<column name="strTools">1x1</column>
			<column name="strConsumed">1x2</column>
			<column name="strDestroyed"></column>
			<column name="nTreasureID">10</column>
			<column name="fHours">0.1</column>
			<column name="nReverse">0</column>
			<column name="nHiddenID">0</column>
			<column name="bIdentify">0</column>
			<column name="bTransferComponents">0</column>
			<column name="vAlsoTry"></column>
			<column name="nTempTreasureID">3</column>
			<column name="bDegradeOutput">0</column>
			<column name="strType">tool</column>
			<column name="bScrap">1</column>
		</table>
		<table name="recipes">
			<column name="nID">3</column>
			<column name="strName">agua esterilizada (pilula)</column>
			<column name="strSecretName">agua esterilizada (pilula)</column>
			<column name="strTools"></column>
			<column name="strConsumed">1x4+1x5</column>
			<column name="strDestroyed"></column>
			<column name="nTreasureID">20</column>
			<column name="fHours">0.1</column>
			<column name="nReverse">0</column>
			<column name="nHiddenID">0</column>
			<column name="bIdentify">1</column>
			<column name="bTransferComponents">0</column>
			<column name="vAlsoTry">75</column>
			<column name="nTempTreasureID">3</column>
			<column name="bDegradeOutput">1</column>
			<column name="strType">food</column>
			<column name="bScrap">1</column>
		</table>
		<table name="recipes">
			<column name="nID">4</column>
			<column name="strName">agua esterilizada (fervida)</column>
			<column name="strSecretName">agua esterilizada (fervida)</column>
			<column name="strTools">1x6+1x7</column>
			<column name="strConsumed">1x4</column>
			<column name="strDestroyed"></column>
			<column name="nTreasureID">20</column>
			<column name="fHours">0.2</column>
			<column name="nReverse">0</column>
			<column name="nHiddenID">0</column>
			<column name="bIdentify">1</column>
			<column name="bTransferComponents">0</column>
			<column name="vAlsoTry">76</column>
			<column name="nTempTreasureID">3</column>
			<column name="bDegradeOutput">1</column>
			<column name="strType">food</column>
			<column name="bScrap">1</column>
		</table>
		<table name="recipes">
			<column name="nID">5</column>
			<column name="strName">cha de tanino</column>
			<column name="strSecretName"></column>
			<column name="strTools">1x6+1x7+1x59</column>
			<column name="strConsumed">1x4+1x8</column>
			<column name="strDestroyed"></column>
			<column name="nTreasureID">137</column>
			<column name="fHours">0.2</column>
			<column name="nReverse">0</column>
			<column name="nHiddenID">0</column>
			<column name="bIdentify">0</column>
			<column name="bTransferComponents">0</column>
			<column name="vAlsoTry"></column>
			<column name="nTempTreasureID">3</column>
			<column name="bDegradeOutput">1</column>
			<column name="strType">medic</column>
			<column name="bScrap">1</column>
		</table>
		<table name="recipes">
			<column name="nID">6</column>
			<column name="strName">carne assada em uma galho</column>
			<column name="strSecretName">carne assada em uma galho (animal)</column>
			<column name="strTools">1x7+1x17</column>
			<column name="strConsumed">1x9</column>
			<column name="strDestroyed"></column>
			<column name="nTreasureID">55</column>
			<column name="fHours">0.2</column>
			<column name="nReverse">0</column>
			<column name="nHiddenID">0</column>
			<column name="bIdentify">0</column>
			<column name="bTransferComponents">0</column>
			<column name="vAlsoTry">71</column>
			<column name="nTempTreasureID">3</column>
			<column name="bDegradeOutput">1</column>
			<column name="strType">food</column>
			<column name="bScrap">1</column>
		</table>
		<table name="recipes">
			<column name="nID">7</column>
			<column name="strName">tunica de retalhos</column>
			<column name="strSecretName"></column>
			<column name="strTools">1x11</column>
			<column name="strConsumed">10x12+20x13</column>
			<column name="strDestroyed"></column>
			<column name="nTreasureID">57</column>
			<column name="fHours">1</column>
			<column name="nReverse">2</column>
			<column name="nHiddenID">0</column>
			<column name="bIdentify">0</column>
			<column name="bTransferComponents">0</column>
			<column name="vAlsoTry"></column>
			<column name="nTempTreasureID">3</column>
			<column name="bDegradeOutput">1</column>
			<column name="strType">misc</column>
			<column name="bScrap">1</column>
		</table>
		<table name="recipes">
			<column name="nID">8</column>
			<column name="strName">carne de um pequeno cadaver</column>
			<column name="strSecretName">carne de um pequeno cadaver (animal)</column>
			<column name="strTools">1x14</column>
			<column name="strConsumed">1x15</column>
			<column name="strDestroyed"></column>
			<column name="nTreasureID">59</column>
			<column name="fHours">0.25</column>
			<column name="nReverse">0</column>
			<column name="nHiddenID">0</column>
			<column name="bIdentify">0</column>
			<column name="bTransferComponents">0</column>
			<column name="vAlsoTry"></column>
			<column name="nTempTreasureID">3</column>
			<column name="bDegradeOutput">1</column>
			<column name="strType">food</column>
			<column name="bScrap">1</column>
		</table>
		<table name="recipes">
			<column name="nID">9</column>
			<column name="strName">Carne e couro de cadaver pequeno e peludo</column>
			<column name="strSecretName">carne e couro de cadaver pequeno e peludo (animal)</column>
			<column name="strTools">1x14+1x16</column>
			<column name="strConsumed">1x41</column>
			<column name="strDestroyed"></column>
			<column name="nTreasureID">60</column>
			<column name="fHours">0.25</column>
			<column name="nReverse">0</column>
			<column name="nHiddenID">0</column>
			<column name="bIdentify">0</column>
			<column name="bTransferComponents">0</column>
			<column name="vAlsoTry"></column>
			<column name="nTempTreasureID">3</column>
			<column name="bDegradeOutput">1</column>
			<column name="strType">food</column>
			<column name="bScrap">1</column>
		</table>
		<table name="recipes">
			<column name="nID">10</column>
			<column name="strName">luva de retalhos</column>
			<column name="strSecretName"></column>
			<column name="strTools">1x11</column>
			<column name="strConsumed">3x12+3x13</column>
			<column name="strDestroyed"></column>
			<column name="nTreasureID">61</column>
			<column name="fHours">0.25</column>
			<column name="nReverse">2</column>
			<column name="nHiddenID">0</column>
			<column name="bIdentify">0</column>
			<column name="bTransferComponents">0</column>
			<column name="vAlsoTry"></column>
			<column name="nTempTreasureID">3</column>
			<column name="bDegradeOutput">1</column>
			<column name="strType">misc</column>
			<column name="bScrap">1</column>
		</table>
		<table name="recipes">
			<column name="nID">11</column>
			<column name="strName">armadilha de esquilo</column>
			<column name="strSecretName"></column>
			<column name="strTools">1x16</column>
			<column name="strConsumed">1x17+2x13</column>
			<column name="strDestroyed"></column>
			<column name="nTreasureID">72</column>
			<column name="fHours">0.1</column>
			<column name="nReverse">1</column>
			<column name="nHiddenID">0</column>
			<column name="bIdentify">0</column>
			<column name="bTransferComponents">0</column>
			<column name="vAlsoTry"></column>
			<column name="nTempTreasureID">3</column>
			<column name="bDegradeOutput">1</column>
			<column name="strType">tool</column>
			<column name="bScrap">1</column>
		</table>
		<table name="recipes">
			<column name="nID">12</column>
			<column name="strName">.308 rifle c/luneta/alca</column>
			<column name="strSecretName"></column>
			<column name="strTools">1x22</column>
			<column name="strConsumed">1x19+1x20+1x18+4x21</column>
			<column name="strDestroyed"></column>
			<column name="nTreasureID">74</column>
			<column name="fHours">0.2</column>
			<column name="nReverse">2</column>
			<column name="nHiddenID">0</column>
			<column name="bIdentify">0</column>
			<column name="bTransferComponents">0</column>
			<column name="vAlsoTry"></column>
			<column name="nTempTreasureID">3</column>
			<column name="bDegradeOutput">1</column>
			<column name="strType">weapon</column>
			<column name="bScrap">1</column>
		</table>
		<table name="recipes">
			<column name="nID">13</column>
			<column name="strName">.308 rifle c/luneta</column>
			<column name="strSecretName"></column>
			<column name="strTools">1x22</column>
			<column name="strConsumed">1x19+1x20+2x21</column>
			<column name="strDestroyed"></column>
			<column name="nTreasureID">75</column>
			<column name="fHours">0.1</column>
			<column name="nReverse">2</column>
			<column name="nHiddenID">0</column>
			<column name="bIdentify">0</column>
			<column name="bTransferComponents">0</column>
			<column name="vAlsoTry"></column>
			<column name="nTempTreasureID">3</column>
			<column name="bDegradeOutput">1</column>
			<column name="strType">weapon</column>
			<column name="bScrap">1</column>
		</table>
		<table name="recipes">
			<column name="nID">14</column>
			<column name="strName">.308 rifle c/alca</column>
			<column name="strSecretName"></column>
			<column name="strTools">1x22</column>
			<column name="strConsumed">1x19+1x18+2x21</column>
			<column name="strDestroyed"></column>
			<column name="nTreasureID">76</column>
			<column name="fHours">0.1</column>
			<column name="nReverse">2</column>
			<column name="nHiddenID">0</column>
			<column name="bIdentify">0</column>
			<column name="bTransferComponents">0</column>
			<column name="vAlsoTry"></column>
			<column name="nTempTreasureID">3</column>
			<column name="bDegradeOutput">1</column>
			<column name="strType">weapon</column>
			<column name="bScrap">1</column>
		</table>
		<table name="recipes">
			<column name="nID">15</column>
			<column name="strName">gazua(chave falsa)</column>
			<column name="strSecretName"></column>
			<column name="strTools">1x23</column>
			<column name="strConsumed">8x21</column>
			<column name="strDestroyed"></column>
			<column name="nTreasureID">86</column>
			<column name="fHours">0.5</column>
			<column name="nReverse">1</column>
			<column name="nHiddenID">0</column>
			<column name="bIdentify">0</column>
			<column name="bTransferComponents">0</column>
			<column name="vAlsoTry"></column>
			<column name="nTempTreasureID">3</column>
			<column name="bDegradeOutput">1</column>
			<column name="strType">tool</column>
			<column name="bScrap">1</column>
		</table>
		<table name="recipes">
			<column name="nID">16</column>
			<column name="strName">curou pequena carne sobre fogueira</column>
			<column name="strSecretName">curou pequena carne sobre fogueira (animal)</column>
			<column name="strTools">1x16+1x7+1x17</column>
			<column name="strConsumed">1x9+1x24</column>
			<column name="strDestroyed"></column>
			<column name="nTreasureID">87</column>
			<column name="fHours">0.25</column>
			<column name="nReverse">0</column>
			<column name="nHiddenID">0</column>
			<column name="bIdentify">0</column>
			<column name="bTransferComponents">0</column>
			<column name="vAlsoTry">72</column>
			<column name="nTempTreasureID">3</column>
			<column name="bDegradeOutput">1</column>
			<column name="strType">food</column>
			<column name="bScrap">1</column>
		</table>
		<table name="recipes">
			<column name="nID">17</column>
			<column name="strName">armadilha de ruido</column>
			<column name="strSecretName"></column>
			<column name="strTools"></column>
			<column name="strConsumed">1x13+1x77+1x25</column>
			<column name="strDestroyed"></column>
			<column name="nTreasureID">91</column>
			<column name="fHours">0.2</column>
			<column name="nReverse">1</column>
			<column name="nHiddenID">0</column>
			<column name="bIdentify">0</column>
			<column name="bTransferComponents">0</column>
			<column name="vAlsoTry"></column>
			<column name="nTempTreasureID">3</column>
			<column name="bDegradeOutput">1</column>
			<column name="strType">tool</column>
			<column name="bScrap">1</column>
		</table>
		<table name="recipes">
			<column name="nID">18</column>
			<column name="strName">abrigo de lona</column>
			<column name="strSecretName"></column>
			<column name="strTools"></column>
			<column name="strConsumed">1x26+2x17+2x18</column>
			<column name="strDestroyed"></column>
			<column name="nTreasureID">93</column>
			<column name="fHours">0.25</column>
			<column name="nReverse">1</column>
			<column name="nHiddenID">0</column>
			<column name="bIdentify">0</column>
			<column name="bTransferComponents">0</column>
			<column name="vAlsoTry"></column>
			<column name="nTempTreasureID">3</column>
			<column name="bDegradeOutput">1</column>
			<column name="strType">tool</column>
			<column name="bScrap">1</column>
		</table>
		<table name="recipes">
			<column name="nID">19</column>
			<column name="strName">tocha bruta</column>
			<column name="strSecretName"></column>
			<column name="strTools"></column>
			<column name="strConsumed">1x10+1x27</column>
			<column name="strDestroyed"></column>
			<column name="nTreasureID">96</column>
			<column name="fHours">0.1</column>
			<column name="nReverse">1</column>
			<column name="nHiddenID">0</column>
			<column name="bIdentify">0</column>
			<column name="bTransferComponents">0</column>
			<column name="vAlsoTry"></column>
			<column name="nTempTreasureID">3</column>
			<column name="bDegradeOutput">1</column>
			<column name="strType">tool</column>
			<column name="bScrap">1</column>
		</table>
		<table name="recipes">
			<column name="nID">20</column>
			<column name="strName">tocha de qualidade</column>
			<column name="strSecretName"></column>
			<column name="strTools"></column>
			<column name="strConsumed">1x10+1x27+2x48</column>
			<column name="strDestroyed"></column>
			<column name="nTreasureID">107</column>
			<column name="fHours">0.15</column>
			<column name="nReverse">1</column>
			<column name="nHiddenID">0</column>
			<column name="bIdentify">0</column>
			<column name="bTransferComponents">0</column>
			<column name="vAlsoTry"></column>
			<column name="nTempTreasureID">3</column>
			<column name="bDegradeOutput">1</column>
			<column name="strType">tool</column>
			<column name="bScrap">1</column>
		</table>
		<table name="recipes">
			<column name="nID">21</column>
			<column name="strName">tocha bruta(acesa)</column>
			<column name="strSecretName"></column>
			<column name="strTools">1x1</column>
			<column name="strConsumed">1x45</column>
			<column name="strDestroyed">2</column>
			<column name="nTreasureID">97</column>
			<column name="fHours">0.1</column>
			<column name="nReverse">1</column>
			<column name="nHiddenID">0</column>
			<column name="bIdentify">0</column>
			<column name="bTransferComponents">1</column>
			<column name="vAlsoTry"></column>
			<column name="nTempTreasureID">3</column>
			<column name="bDegradeOutput">1</column>
			<column name="strType">tool</column>
			<column name="bScrap">1</column>
		</table>
		<table name="recipes">
			<column name="nID">22</column>
			<column name="strName">tocha de qualidade(acesa)</column>
			<column name="strSecretName"></column>
			<column name="strTools">1x1</column>
			<column name="strConsumed">1x46</column>
			<column name="strDestroyed">2</column>
			<column name="nTreasureID">102</column>
			<column name="fHours">0.15</column>
			<column name="nReverse">1</column>
			<column name="nHiddenID">0</column>
			<column name="bIdentify">0</column>
			<column name="bTransferComponents">1</column>
			<column name="vAlsoTry"></column>
			<column name="nTempTreasureID">3</column>
			<column name="bDegradeOutput">1</column>
			<column name="strType">tool</column>
			<column name="bScrap">1</column>
		</table>
		<table name="recipes">
			<column name="nID">23</column>
			<column name="strName">trapos de roupas</column>
			<column name="strSecretName"></column>
			<column name="strTools"></column>
			<column name="strConsumed">1x28</column>
			<column name="strDestroyed"></column>
			<column name="nTreasureID">11</column>
			<column name="fHours">0.1</column>
			<column name="nReverse">0</column>
			<column name="nHiddenID">0</column>
			<column name="bIdentify">0</column>
			<column name="bTransferComponents">0</column>
			<column name="vAlsoTry"></column>
			<column name="nTempTreasureID">3</column>
			<column name="bDegradeOutput">1</column>
			<column name="strType">misc</column>
			<column name="bScrap">1</column>
		</table>
		<table name="recipes">
			<column name="nID">24</column>
			<column name="strName">panos limpos (cozidos)</column>
			<column name="strSecretName"></column>
			<column name="strTools">1x6+1x7</column>
			<column name="strConsumed">1x29+1x30</column>
			<column name="strDestroyed"></column>
			<column name="nTreasureID">139</column>
			<column name="fHours">0.2</column>
			<column name="nReverse">0</column>
			<column name="nHiddenID">0</column>
			<column name="bIdentify">0</column>
			<column name="bTransferComponents">0</column>
			<column name="vAlsoTry"></column>
			<column name="nTempTreasureID">3</column>
			<column name="bDegradeOutput">1</column>
			<column name="strType">medic</column>
			<column name="bScrap">1</column>
		</table>
		<table name="recipes">
			<column name="nID">25</column>
			<column name="strName">panos limpos (desinfetante)</column>
			<column name="strSecretName"></column>
			<column name="strTools"></column>
			<column name="strConsumed">1x30+1x31</column>
			<column name="strDestroyed"></column>
			<column name="nTreasureID">139</column>
			<column name="fHours">0.05</column>
			<column name="nReverse">0</column>
			<column name="nHiddenID">0</column>
			<column name="bIdentify">0</column>
			<column name="bTransferComponents">0</column>
			<column name="vAlsoTry"></column>
			<column name="nTempTreasureID">3</column>
			<column name="bDegradeOutput">1</column>
			<column name="strType">medic</column>
			<column name="bScrap">1</column>
		</table>
		<table name="recipes">
			<column name="nID">26</column>
			<column name="strName">tala de madeira</column>
			<column name="strSecretName"></column>
			<column name="strTools"></column>
			<column name="strConsumed">1x10+2x42</column>
			<column name="strDestroyed"></column>
			<column name="nTreasureID">148</column>
			<column name="fHours">0.15</column>
			<column name="nReverse">1</column>
			<column name="nHiddenID">0</column>
			<column name="bIdentify">0</column>
			<column name="bTransferComponents">0</column>
			<column name="vAlsoTry"></column>
			<column name="nTempTreasureID">3</column>
			<column name="bDegradeOutput">1</column>
			<column name="strType">medic</column>
			<column name="bScrap">1</column>
		</table>
		<table name="recipes">
			<column name="nID">27</column>
			<column name="strName">recursos rio/pantano/lago</column>
			<column name="strSecretName"></column>
			<column name="strTools">1x33</column>
			<column name="strConsumed"></column>
			<column name="strDestroyed"></column>
			<column name="nTreasureID">150</column>
			<column name="fHours">0</column>
			<column name="nReverse">0</column>
			<column name="nHiddenID">0</column>
			<column name="bIdentify">0</column>
			<column name="bTransferComponents">0</column>
			<column name="vAlsoTry"></column>
			<column name="nTempTreasureID">3</column>
			<column name="bDegradeOutput">1</column>
			<column name="strType">misc</column>
			<column name="bScrap">1</column>
		</table>
		<table name="recipes">
			<column name="nID">28</column>
			<column name="strName">recursos florestais</column>
			<column name="strSecretName"></column>
			<column name="strTools">1x34</column>
			<column name="strConsumed"></column>
			<column name="strDestroyed"></column>
			<column name="nTreasureID">153</column>
			<column name="fHours">0</column>
			<column name="nReverse">0</column>
			<column name="nHiddenID">0</column>
			<column name="bIdentify">0</column>
			<column name="bTransferComponents">0</column>
			<column name="vAlsoTry"></column>
			<column name="nTempTreasureID">3</column>
			<column name="bDegradeOutput">1</column>
			<column name="strType">misc</column>
			<column name="bScrap">1</column>
		</table>
		<table name="recipes">
			<column name="nID">29</column>
			<column name="strName">HVAC (aquecido)</column>
			<column name="strSecretName"></column>
			<column name="strTools">1x35+1x22</column>
			<column name="strConsumed">1x36+4x21+1x37</column>
			<column name="strDestroyed"></column>
			<column name="nTreasureID">159</column>
			<column name="fHours">0.25</column>
			<column name="nReverse">2</column>
			<column name="nHiddenID">0</column>
			<column name="bIdentify">0</column>
			<column name="bTransferComponents">0</column>
			<column name="vAlsoTry"></column>
			<column name="nTempTreasureID">3</column>
			<column name="bDegradeOutput">1</column>
			<column name="strType">tool</column>
			<column name="bScrap">1</column>
		</table>
		<table name="recipes">
			<column name="nID">30</column>
			<column name="strName">iluminacao Cryo</column>
			<column name="strSecretName"></column>
			<column name="strTools">1x39+1x14+1x40</column>
			<column name="strConsumed">1x38+4x21</column>
			<column name="strDestroyed"></column>
			<column name="nTreasureID">161</column>
			<column name="fHours">0.25</column>
			<column name="nReverse">2</column>
			<column name="nHiddenID">0</column>
			<column name="bIdentify">0</column>
			<column name="bTransferComponents">0</column>
			<column name="vAlsoTry"></column>
			<column name="nTempTreasureID">3</column>
			<column name="bDegradeOutput">1</column>
			<column name="strType">tool</column>
			<column name="bScrap">1</column>
		</table>
		<table name="recipes">
			<column name="nID">31</column>
			<column name="strName">fogueira media extinta</column>
			<column name="strSecretName"></column>
			<column name="strTools"></column>
			<column name="strConsumed">1x128</column>
			<column name="strDestroyed"></column>
			<column name="nTreasureID">89</column>
			<column name="fHours">0.01</column>
			<column name="nReverse">0</column>
			<column name="nHiddenID">0</column>
			<column name="bIdentify">0</column>
			<column name="bTransferComponents">0</column>
			<column name="vAlsoTry"></column>
			<column name="nTempTreasureID">3</column>
			<column name="bDegradeOutput">1</column>
			<column name="strType">misc</column>
			<column name="bScrap">1</column>
		</table>
		<table name="recipes">
			<column name="nID">32</column>
			<column name="strName">extinguida pequena fogueira</column>
			<column name="strSecretName"></column>
			<column name="strTools"></column>
			<column name="strConsumed">1x43</column>
			<column name="strDestroyed"></column>
			<column name="nTreasureID">18</column>
			<column name="fHours">0.01</column>
			<column name="nReverse">0</column>
			<column name="nHiddenID">0</column>
			<column name="bIdentify">0</column>
			<column name="bTransferComponents">0</column>
			<column name="vAlsoTry"></column>
			<column name="nTempTreasureID">3</column>
			<column name="bDegradeOutput">1</column>
			<column name="strType">misc</column>
			<column name="bScrap">1</column>
		</table>
		<table name="recipes">
			<column name="nID">33</column>
			<column name="strName">fogueira media (abastecida)</column>
			<column name="strSecretName"></column>
			<column name="strTools"></column>
			<column name="strConsumed">1x43+1x3</column>
			<column name="strDestroyed"></column>
			<column name="nTreasureID">8</column>
			<column name="fHours">0.15</column>
			<column name="nReverse">0</column>
			<column name="nHiddenID">0</column>
			<column name="bIdentify">0</column>
			<column name="bTransferComponents">0</column>
			<column name="vAlsoTry"></column>
			<column name="nTempTreasureID">3</column>
			<column name="bDegradeOutput">0</column>
			<column name="strType">tool</column>
			<column name="bScrap">1</column>
		</table>
		<table name="recipes">
			<column name="nID">34</column>
			<column name="strName">pequena fogueira (friccao)</column>
			<column name="strSecretName"></column>
			<column name="strTools">2x50+1x16</column>
			<column name="strConsumed">1x2</column>
			<column name="strDestroyed"></column>
			<column name="nTreasureID">10</column>
			<column name="fHours">0.3</column>
			<column name="nReverse">0</column>
			<column name="nHiddenID">0</column>
			<column name="bIdentify">0</column>
			<column name="bTransferComponents">0</column>
			<column name="vAlsoTry"></column>
			<column name="nTempTreasureID">3</column>
			<column name="bDegradeOutput">0</column>
			<column name="strType">tool</column>
			<column name="bScrap">1</column>
		</table>
		<table name="recipes">
			<column name="nID">35</column>
			<column name="strName">fio medio</column>
			<column name="strSecretName"></column>
			<column name="strTools"></column>
			<column name="strConsumed">3x13</column>
			<column name="strDestroyed"></column>
			<column name="nTreasureID">100</column>
			<column name="fHours">0.01</column>
			<column name="nReverse">1</column>
			<column name="nHiddenID">0</column>
			<column name="bIdentify">0</column>
			<column name="bTransferComponents">0</column>
			<column name="vAlsoTry"></column>
			<column name="nTempTreasureID">3</column>
			<column name="bDegradeOutput">1</column>
			<column name="strType">misc</column>
			<column name="bScrap">1</column>
		</table>
		<table name="recipes">
			<column name="nID">36</column>
			<column name="strName">pe de cabra c/alca</column>
			<column name="strSecretName"></column>
			<column name="strTools"></column>
			<column name="strConsumed">1x18+1x52</column>
			<column name="strDestroyed"></column>
			<column name="nTreasureID">103</column>
			<column name="fHours">0.01</column>
			<column name="nReverse">1</column>
			<column name="nHiddenID">0</column>
			<column name="bIdentify">0</column>
			<column name="bTransferComponents">0</column>
			<column name="vAlsoTry"></column>
			<column name="nTempTreasureID">3</column>
			<column name="bDegradeOutput">1</column>
			<column name="strType">weapon</column>
			<column name="bScrap">1</column>
		</table>
		<table name="recipes">
			<column name="nID">37</column>
			<column name="strName">binoculos c/alca</column>
			<column name="strSecretName"></column>
			<column name="strTools"></column>
			<column name="strConsumed">1x18+1x53</column>
			<column name="strDestroyed"></column>
			<column name="nTreasureID">104</column>
			<column name="fHours">0.01</column>
			<column name="nReverse">1</column>
			<column name="nHiddenID">0</column>
			<column name="bIdentify">0</column>
			<column name="bTransferComponents">0</column>
			<column name="vAlsoTry"></column>
			<column name="nTempTreasureID">3</column>
			<column name="bDegradeOutput">1</column>
			<column name="strType">tool</column>
			<column name="bScrap">1</column>
		</table>
		<table name="recipes">
			<column name="nID">38</column>
			<column name="strName">binoculos</column>
			<column name="strSecretName"></column>
			<column name="strTools">1x22+1x35+1x40</column>
			<column name="strConsumed">5x21+2x20</column>
			<column name="strDestroyed"></column>
			<column name="nTreasureID">105</column>
			<column name="fHours">0.01</column>
			<column name="nReverse">2</column>
			<column name="nHiddenID">0</column>
			<column name="bIdentify">0</column>
			<column name="bTransferComponents">0</column>
			<column name="vAlsoTry"></column>
			<column name="nTempTreasureID">3</column>
			<column name="bDegradeOutput">1</column>
			<column name="strType">tool</column>
			<column name="bScrap">1</column>
		</table>
		<table name="recipes">
			<column name="nID">39</column>
			<column name="strName">luneta c/alca</column>
			<column name="strSecretName"></column>
			<column name="strTools"></column>
			<column name="strConsumed">1x18+1x20</column>
			<column name="strDestroyed"></column>
			<column name="nTreasureID">142</column>
			<column name="fHours">0.01</column>
			<column name="nReverse">1</column>
			<column name="nHiddenID">0</column>
			<column name="bIdentify">0</column>
			<column name="bTransferComponents">0</column>
			<column name="vAlsoTry"></column>
			<column name="nTempTreasureID">3</column>
			<column name="bDegradeOutput">1</column>
			<column name="strType">tool</column>
			<column name="bScrap">1</column>
		</table>
		<table name="recipes">
			<column name="nID">40</column>
			<column name="strName">carrinho de caixa</column>
			<column name="strSecretName"></column>
			<column name="strTools">1x40+1x22+1x35</column>
			<column name="strConsumed">2x54+16x21+1x55+4x56+6x13</column>
			<column name="strDestroyed"></column>
			<column name="nTreasureID">356</column>
			<column name="fHours">1</column>
			<column name="nReverse">2</column>
			<column name="nHiddenID">0</column>
			<column name="bIdentify">0</column>
			<column name="bTransferComponents">0</column>
			<column name="vAlsoTry"></column>
			<column name="nTempTreasureID">3</column>
			<column name="bDegradeOutput">1</column>
			<column name="strType">tool</column>
			<column name="bScrap">1</column>
		</table>
		<table name="recipes">
			<column name="nID">41</column>
			<column name="strName">carrinho de compras</column>
			<column name="strSecretName"></column>
			<column name="strTools">1x40+1x22+1x35</column>
			<column name="strConsumed">1x57+16x21+1x55+4x56</column>
			<column name="strDestroyed"></column>
			<column name="nTreasureID">364</column>
			<column name="fHours">1</column>
			<column name="nReverse">2</column>
			<column name="nHiddenID">0</column>
			<column name="bIdentify">0</column>
			<column name="bTransferComponents">0</column>
			<column name="vAlsoTry"></column>
			<column name="nTempTreasureID">3</column>
			<column name="bDegradeOutput">1</column>
			<column name="strType">tool</column>
			<column name="bScrap">1</column>
		</table>
		<table name="recipes">
			<column name="nID">42</column>
			<column name="strName">treno de plastico c/alca</column>
			<column name="strSecretName"></column>
			<column name="strTools"></column>
			<column name="strConsumed">2x18+1x58</column>
			<column name="strDestroyed"></column>
			<column name="nTreasureID">367</column>
			<column name="fHours">0.01</column>
			<column name="nReverse">1</column>
			<column name="nHiddenID">0</column>
			<column name="bIdentify">0</column>
			<column name="bTransferComponents">0</column>
			<column name="vAlsoTry"></column>
			<column name="nTempTreasureID">3</column>
			<column name="bDegradeOutput">1</column>
			<column name="strType">tool</column>
			<column name="bScrap">1</column>
		</table>
		<table name="recipes">
			<column name="nID">43</column>
			<column name="strName">travois</column>
			<column name="strSecretName"></column>
			<column name="strTools">1x35</column>
			<column name="strConsumed">2x60+4x10+12x18</column>
			<column name="strDestroyed"></column>
			<column name="nTreasureID">369</column>
			<column name="fHours">1</column>
			<column name="nReverse">1</column>
			<column name="nHiddenID">0</column>
			<column name="bIdentify">0</column>
			<column name="bTransferComponents">0</column>
			<column name="vAlsoTry"></column>
			<column name="nTempTreasureID">3</column>
			<column name="bDegradeOutput">1</column>
			<column name="strType">tool</column>
			<column name="bScrap">1</column>
		</table>
		<table name="recipes">
			<column name="nID">44</column>
			<column name="strName">garrafa quebrado</column>
			<column name="strSecretName"></column>
			<column name="strTools"></column>
			<column name="strConsumed">1x61</column>
			<column name="strDestroyed"></column>
			<column name="nTreasureID">370</column>
			<column name="fHours">0.01</column>
			<column name="nReverse">0</column>
			<column name="nHiddenID">0</column>
			<column name="bIdentify">0</column>
			<column name="bTransferComponents">0</column>
			<column name="vAlsoTry"></column>
			<column name="nTempTreasureID">3</column>
			<column name="bDegradeOutput">0</column>
			<column name="strType">misc</column>
			<column name="bScrap">1</column>
		</table>
		<table name="recipes">
			<column name="nID">45</column>
			<column name="strName">caco de vidro</column>
			<column name="strSecretName"></column>
			<column name="strTools"></column>
			<column name="strConsumed">1x62</column>
			<column name="strDestroyed"></column>
			<column name="nTreasureID">371</column>
			<column name="fHours">0.01</column>
			<column name="nReverse">0</column>
			<column name="nHiddenID">0</column>
			<column name="bIdentify">0</column>
			<column name="bTransferComponents">0</column>
			<column name="vAlsoTry"></column>
			<column name="nTempTreasureID">3</column>
			<column name="bDegradeOutput">0</column>
			<column name="strType">misc</column>
			<column name="bScrap">1</column>
		</table>
		<table name="recipes">
			<column name="nID">46</column>
			<column name="strName">enrolado</column>
			<column name="strSecretName"></column>
			<column name="strTools"></column>
			<column name="strConsumed">1x63+1x42</column>
			<column name="strDestroyed"></column>
			<column name="nTreasureID">372</column>
			<column name="fHours">0.05</column>
			<column name="nReverse">1</column>
			<column name="nHiddenID">0</column>
			<column name="bIdentify">0</column>
			<column name="bTransferComponents">0</column>
			<column name="vAlsoTry"></column>
			<column name="nTempTreasureID">3</column>
			<column name="bDegradeOutput">1</column>
			<column name="strType">weapon</column>
			<column name="bScrap">1</column>
		</table>
		<table name="recipes">
			<column name="nID">47</column>
			<column name="strName">arco: composto c/alca</column>
			<column name="strSecretName"></column>
			<column name="strTools"></column>
			<column name="strConsumed">1x18+1x64</column>
			<column name="strDestroyed"></column>
			<column name="nTreasureID">377</column>
			<column name="fHours">0.01</column>
			<column name="nReverse">1</column>
			<column name="nHiddenID">0</column>
			<column name="bIdentify">0</column>
			<column name="bTransferComponents">0</column>
			<column name="vAlsoTry"></column>
			<column name="nTempTreasureID">3</column>
			<column name="bDegradeOutput">1</column>
			<column name="strType">weapon</column>
			<column name="bScrap">1</column>
		</table>
		<table name="recipes">
			<column name="nID">48</column>
			<column name="strName">arco: madeira verde</column>
			<column name="strSecretName"></column>
			<column name="strTools">1x14+1x51</column>
			<column name="strConsumed">1x18+1x65</column>
			<column name="strDestroyed"></column>
			<column name="nTreasureID">428</column>
			<column name="fHours">1</column>
			<column name="nReverse">1</column>
			<column name="nHiddenID">0</column>
			<column name="bIdentify">1</column>
			<column name="bTransferComponents">0</column>
			<column name="vAlsoTry"></column>
			<column name="nTempTreasureID">3</column>
			<column name="bDegradeOutput">1</column>
			<column name="strType">weapon</column>
			<column name="bScrap">1</column>
		</table>
		<table name="recipes">
			<column name="nID">49</column>
			<column name="strName">flecha: bruto/cabeca larga</column>
			<column name="strSecretName"></column>
			<column name="strTools">1x14+1x51</column>
			<column name="strConsumed">1x13+1x80+1x66+3x67</column>
			<column name="strDestroyed"></column>
			<column name="nTreasureID">381</column>
			<column name="fHours">1</column>
			<column name="nReverse">1</column>
			<column name="nHiddenID">0</column>
			<column name="bIdentify">1</column>
			<column name="bTransferComponents">0</column>
			<column name="vAlsoTry"></column>
			<column name="nTempTreasureID">3</column>
			<column name="bDegradeOutput">1</column>
			<column name="strType">weapon</column>
			<column name="bScrap">1</column>
		</table>
		<table name="recipes">
			<column name="nID">50</column>
			<column name="strName">flexa: bruto/penetrante</column>
			<column name="strSecretName"></column>
			<column name="strTools">1x14+1x51</column>
			<column name="strConsumed">1x13+1x80+1x68+3x67</column>
			<column name="strDestroyed"></column>
			<column name="nTreasureID">380</column>
			<column name="fHours">1</column>
			<column name="nReverse">1</column>
			<column name="nHiddenID">0</column>
			<column name="bIdentify">1</column>
			<column name="bTransferComponents">0</column>
			<column name="vAlsoTry"></column>
			<column name="nTempTreasureID">3</column>
			<column name="bDegradeOutput">1</column>
			<column name="strType">weapon</column>
			<column name="bScrap">1</column>
		</table>
		<table name="recipes">
			<column name="nID">51</column>
			<column name="strName">estilingue</column>
			<column name="strSecretName"></column>
			<column name="strTools"></column>
			<column name="strConsumed">2x18+1x32</column>
			<column name="strDestroyed"></column>
			<column name="nTreasureID">384</column>
			<column name="fHours">0.2</column>
			<column name="nReverse">1</column>
			<column name="nHiddenID">0</column>
			<column name="bIdentify">0</column>
			<column name="bTransferComponents">0</column>
			<column name="vAlsoTry"></column>
			<column name="nTempTreasureID">3</column>
			<column name="bDegradeOutput">1</column>
			<column name="strType">weapon</column>
			<column name="bScrap">1</column>
		</table>
		<table name="recipes">
			<column name="nID">52</column>
			<column name="strName">espingarda c/alca</column>
			<column name="strSecretName"></column>
			<column name="strTools">1x22</column>
			<column name="strConsumed">1x69+1x18+2x21</column>
			<column name="strDestroyed"></column>
			<column name="nTreasureID">386</column>
			<column name="fHours">0.1</column>
			<column name="nReverse">2</column>
			<column name="nHiddenID">0</column>
			<column name="bIdentify">0</column>
			<column name="bTransferComponents">0</column>
			<column name="vAlsoTry"></column>
			<column name="nTempTreasureID">3</column>
			<column name="bDegradeOutput">1</column>
			<column name="strType">weapon</column>
			<column name="bScrap">1</column>
		</table>
		<table name="recipes">
			<column name="nID">53</column>
			<column name="strName">lanca afiada</column>
			<column name="strSecretName"></column>
			<column name="strTools">1x14</column>
			<column name="strConsumed">1x65</column>
			<column name="strDestroyed"></column>
			<column name="nTreasureID">389</column>
			<column name="fHours">0.5</column>
			<column name="nReverse">0</column>
			<column name="nHiddenID">0</column>
			<column name="bIdentify">0</column>
			<column name="bTransferComponents">0</column>
			<column name="vAlsoTry"></column>
			<column name="nTempTreasureID">3</column>
			<column name="bDegradeOutput">1</column>
			<column name="strType">weapon</column>
			<column name="bScrap">1</column>
		</table>
		<table name="recipes">
			<column name="nID">54</column>
			<column name="strName">lanca endurecida</column>
			<column name="strSecretName"></column>
			<column name="strTools">1x14+1x76+1x1</column>
			<column name="strConsumed">1x65</column>
			<column name="strDestroyed"></column>
			<column name="nTreasureID">390</column>
			<column name="fHours">1</column>
			<column name="nReverse">0</column>
			<column name="nHiddenID">0</column>
			<column name="bIdentify">0</column>
			<column name="bTransferComponents">0</column>
			<column name="vAlsoTry"></column>
			<column name="nTempTreasureID">3</column>
			<column name="bDegradeOutput">1</column>
			<column name="strType">weapon</column>
			<column name="bScrap">1</column>
		</table>
		<table name="recipes">
			<column name="nID">55</column>
			<column name="strName">lanca larga</column>
			<column name="strSecretName"></column>
			<column name="strTools">1x14+1x76</column>
			<column name="strConsumed">1x65+1x66+1x42</column>
			<column name="strDestroyed"></column>
			<column name="nTreasureID">391</column>
			<column name="fHours">1</column>
			<column name="nReverse">1</column>
			<column name="nHiddenID">0</column>
			<column name="bIdentify">0</column>
			<column name="bTransferComponents">0</column>
			<column name="vAlsoTry"></column>
			<column name="nTempTreasureID">3</column>
			<column name="bDegradeOutput">1</column>
			<column name="strType">weapon</column>
			<column name="bScrap">1</column>
		</table>
		<table name="recipes">
			<column name="nID">56</column>
			<column name="strName">agua esterilizada x2 (fervida)</column>
			<column name="strSecretName">agua esterilizada x2 (fervida) (pura)</column>
			<column name="strTools">1x70+1x7</column>
			<column name="strConsumed">2x4</column>
			<column name="strDestroyed"></column>
			<column name="nTreasureID">108</column>
			<column name="fHours">0.4</column>
			<column name="nReverse">0</column>
			<column name="nHiddenID">0</column>
			<column name="bIdentify">1</column>
			<column name="bTransferComponents">0</column>
			<column name="vAlsoTry">77</column>
			<column name="nTempTreasureID">3</column>
			<column name="bDegradeOutput">1</column>
			<column name="strType">food</column>
			<column name="bScrap">1</column>
		</table>
		<table name="recipes">
			<column name="nID">57</column>
			<column name="strName">agua esterilizada x3 (fervida)</column>
			<column name="strSecretName">agua esterilizada x3 (fervida) (pura)</column>
			<column name="strTools">1x70+1x7</column>
			<column name="strConsumed">3x4</column>
			<column name="strDestroyed"></column>
			<column name="nTreasureID">109</column>
			<column name="fHours">0.6</column>
			<column name="nReverse">0</column>
			<column name="nHiddenID">0</column>
			<column name="bIdentify">1</column>
			<column name="bTransferComponents">0</column>
			<column name="vAlsoTry">78</column>
			<column name="nTempTreasureID">3</column>
			<column name="bDegradeOutput">1</column>
			<column name="strType">food</column>
			<column name="bScrap">1</column>
		</table>
		<table name="recipes">
			<column name="nID">58</column>
			<column name="strName">trapos limpos x2 (cozidos)</column>
			<column name="strSecretName"></column>
			<column name="strTools">1x70+1x7</column>
			<column name="strConsumed">1x29+2x30</column>
			<column name="strDestroyed"></column>
			<column name="nTreasureID">140</column>
			<column name="fHours">0.4</column>
			<column name="nReverse">0</column>
			<column name="nHiddenID">0</column>
			<column name="bIdentify">0</column>
			<column name="bTransferComponents">0</column>
			<column name="vAlsoTry"></column>
			<column name="nTempTreasureID">3</column>
			<column name="bDegradeOutput">1</column>
			<column name="strType">medic</column>
			<column name="bScrap">1</column>
		</table>
		<table name="recipes">
			<column name="nID">59</column>
			<column name="strName">trapos limpos x3 (cozidos)</column>
			<column name="strSecretName"></column>
			<column name="strTools">1x70+1x7</column>
			<column name="strConsumed">1x29+3x30</column>
			<column name="strDestroyed"></column>
			<column name="nTreasureID">141</column>
			<column name="fHours">0.6</column>
			<column name="nReverse">0</column>
			<column name="nHiddenID">0</column>
			<column name="bIdentify">0</column>
			<column name="bTransferComponents">0</column>
			<column name="vAlsoTry"></column>
			<column name="nTempTreasureID">3</column>
			<column name="bDegradeOutput">1</column>
			<column name="strType">medic</column>
			<column name="bScrap">1</column>
		</table>
		<table name="recipes">
			<column name="nID">60</column>
			<column name="strName">carne de grande cadaver</column>
			<column name="strSecretName">carne de grande cadaver (animal)</column>
			<column name="strTools">1x14</column>
			<column name="strConsumed">1x71</column>
			<column name="strDestroyed"></column>
			<column name="nTreasureID">399</column>
			<column name="fHours">1</column>
			<column name="nReverse">0</column>
			<column name="nHiddenID">0</column>
			<column name="bIdentify">0</column>
			<column name="bTransferComponents">0</column>
			<column name="vAlsoTry"></column>
			<column name="nTempTreasureID">3</column>
			<column name="bDegradeOutput">1</column>
			<column name="strType">food</column>
			<column name="bScrap">1</column>
		</table>
		<table name="recipes">
			<column name="nID">61</column>
			<column name="strName">carne e couro de um Lobisomem</column>
			<column name="strSecretName">carne e couro de um Lobisomem(animal)</column>
			<column name="strTools">1x14+1x16</column>
			<column name="strConsumed">1x72</column>
			<column name="strDestroyed"></column>
			<column name="nTreasureID">400</column>
			<column name="fHours">1</column>
			<column name="nReverse">0</column>
			<column name="nHiddenID">0</column>
			<column name="bIdentify">0</column>
			<column name="bTransferComponents">0</column>
			<column name="vAlsoTry"></column>
			<column name="nTempTreasureID">3</column>
			<column name="bDegradeOutput">1</column>
			<column name="strType">food</column>
			<column name="bScrap">1</column>
		</table>
		<table name="recipes">
			<column name="nID">62</column>
			<column name="strName">carne de cadaver grande e peludo</column>
			<column name="strSecretName">carne de cadaver grande e peludo (animal)</column>
			<column name="strTools">1x14</column>
			<column name="strConsumed">1x73</column>
			<column name="strDestroyed"></column>
			<column name="nTreasureID">403</column>
			<column name="fHours">1</column>
			<column name="nReverse">0</column>
			<column name="nHiddenID">0</column>
			<column name="bIdentify">0</column>
			<column name="bTransferComponents">0</column>
			<column name="vAlsoTry"></column>
			<column name="nTempTreasureID">3</column>
			<column name="bDegradeOutput">1</column>
			<column name="strType">food</column>
			<column name="bScrap">1</column>
		</table>
		<table name="recipes">
			<column name="nID">63</column>
			<column name="strName">carne assada em uma galho (media)</column>
			<column name="strSecretName">carne assada em uma galho (media)(animal)</column>
			<column name="strTools">1x7+1x17</column>
			<column name="strConsumed">1x74</column>
			<column name="strDestroyed"></column>
			<column name="nTreasureID">405</column>
			<column name="fHours">0.4</column>
			<column name="nReverse">0</column>
			<column name="nHiddenID">0</column>
			<column name="bIdentify">0</column>
			<column name="bTransferComponents">0</column>
			<column name="vAlsoTry">73</column>
			<column name="nTempTreasureID">3</column>
			<column name="bDegradeOutput">1</column>
			<column name="strType">food</column>
			<column name="bScrap">1</column>
		</table>
		<table name="recipes">
			<column name="nID">64</column>
			<column name="strName">carne seca curada sobre fogueira</column>
			<column name="strSecretName">carne seca curada sobre fogueira (animal)</column>
			<column name="strTools">1x16+1x7+1x17</column>
			<column name="strConsumed">1x74+2x24</column>
			<column name="strDestroyed"></column>
			<column name="nTreasureID">56</column>
			<column name="fHours">0.5</column>
			<column name="nReverse">0</column>
			<column name="nHiddenID">0</column>
			<column name="bIdentify">0</column>
			<column name="bTransferComponents">0</column>
			<column name="vAlsoTry">74</column>
			<column name="nTempTreasureID">3</column>
			<column name="bDegradeOutput">1</column>
			<column name="strType">food</column>
			<column name="bScrap">1</column>
		</table>
		<table name="recipes">
			<column name="nID">65</column>
			<column name="strName">carne media de um cadaver peludo</column>
			<column name="strSecretName">carne media de um cadaver peludo(animal)</column>
			<column name="strTools">1x14</column>
			<column name="strConsumed">1x75</column>
			<column name="strDestroyed"></column>
			<column name="nTreasureID">407</column>
			<column name="fHours">1</column>
			<column name="nReverse">0</column>
			<column name="nHiddenID">0</column>
			<column name="bIdentify">0</column>
			<column name="bTransferComponents">0</column>
			<column name="vAlsoTry"></column>
			<column name="nTempTreasureID">3</column>
			<column name="bDegradeOutput">1</column>
			<column name="strType">food</column>
			<column name="bScrap">1</column>
		</table>
		<table name="recipes">
			<column name="nID">66</column>
			<column name="strName">carne e couro medio de um cadaver peludo</column>
			<column name="strSecretName">carne e couro medio de um cadaver peludo(animal)</column>
			<column name="strTools">1x14+1x16</column>
			<column name="strConsumed">1x75</column>
			<column name="strDestroyed"></column>
			<column name="nTreasureID">408</column>
			<column name="fHours">1</column>
			<column name="nReverse">0</column>
			<column name="nHiddenID">0</column>
			<column name="bIdentify">0</column>
			<column name="bTransferComponents">0</column>
			<column name="vAlsoTry"></column>
			<column name="nTempTreasureID">3</column>
			<column name="bDegradeOutput">1</column>
			<column name="strType">food</column>
			<column name="bScrap">1</column>
		</table>
		<table name="recipes">
			<column name="nID">67</column>
			<column name="strName">restos de papel</column>
			<column name="strSecretName"></column>
			<column name="strTools"></column>
			<column name="strConsumed">1x79</column>
			<column name="strDestroyed"></column>
			<column name="nTreasureID">429</column>
			<column name="fHours">0.01</column>
			<column name="nReverse">0</column>
			<column name="nHiddenID">0</column>
			<column name="bIdentify">0</column>
			<column name="bTransferComponents">0</column>
			<column name="vAlsoTry"></column>
			<column name="nTempTreasureID">3</column>
			<column name="bDegradeOutput">1</column>
			<column name="strType">misc</column>
			<column name="bScrap">1</column>
		</table>
		<table name="recipes">
			<column name="nID">68</column>
			<column name="strName">.308 rifle c/luneta, add/alca</column>
			<column name="strSecretName"></column>
			<column name="strTools">1x22</column>
			<column name="strConsumed">1x81+1x18+2x21</column>
			<column name="strDestroyed"></column>
			<column name="nTreasureID">74</column>
			<column name="fHours">0.1</column>
			<column name="nReverse">2</column>
			<column name="nHiddenID">0</column>
			<column name="bIdentify">0</column>
			<column name="bTransferComponents">0</column>
			<column name="vAlsoTry"></column>
			<column name="nTempTreasureID">3</column>
			<column name="bDegradeOutput">1</column>
			<column name="strType">weapon</column>
			<column name="bScrap">1</column>
		</table>
		<table name="recipes">
			<column name="nID">69</column>
			<column name="strName">.308 rifle c/correia, add/luneta</column>
			<column name="strSecretName"></column>
			<column name="strTools">1x22</column>
			<column name="strConsumed">1x82+1x20+2x21</column>
			<column name="strDestroyed"></column>
			<column name="nTreasureID">74</column>
			<column name="fHours">0.1</column>
			<column name="nReverse">2</column>
			<column name="nHiddenID">0</column>
			<column name="bIdentify">0</column>
			<column name="bTransferComponents">0</column>
			<column name="vAlsoTry"></column>
			<column name="nTempTreasureID">3</column>
			<column name="bDegradeOutput">1</column>
			<column name="strType">weapon</column>
			<column name="bScrap">1</column>
		</table>
		<table name="recipes">
			<column name="nID">70</column>
			<column name="strName">carne de cadaver humanoide</column>
			<column name="strSecretName">carne de cadaver humanoide (humano)</column>
			<column name="strTools">1x14</column>
			<column name="strConsumed">1x91</column>
			<column name="strDestroyed"></column>
			<column name="nTreasureID">470</column>
			<column name="fHours">1</column>
			<column name="nReverse">0</column>
			<column name="nHiddenID">0</column>
			<column name="bIdentify">0</column>
			<column name="bTransferComponents">0</column>
			<column name="vAlsoTry"></column>
			<column name="nTempTreasureID">3</column>
			<column name="bDegradeOutput">1</column>
			<column name="strType">food</column>
			<column name="bScrap">1</column>
		</table>
		<table name="recipes">
			<column name="nID">71</column>
			<column name="strName">carne assada em uma galho</column>
			<column name="strSecretName">carne assada em uma galho(humano)</column>
			<column name="strTools">1x7+1x17</column>
			<column name="strConsumed">1x85</column>
			<column name="strDestroyed"></column>
			<column name="nTreasureID">477</column>
			<column name="fHours">0.2</column>
			<column name="nReverse">0</column>
			<column name="nHiddenID">6</column>
			<column name="bIdentify">0</column>
			<column name="bTransferComponents">0</column>
			<column name="vAlsoTry"></column>
			<column name="nTempTreasureID">3</column>
			<column name="bDegradeOutput">1</column>
			<column name="strType">food</column>
			<column name="bScrap">1</column>
		</table>
		<table name="recipes">
			<column name="nID">72</column>
			<column name="strName">curou pequena carne sobre fogueira</column>
			<column name="strSecretName">curou pequena carne sobre a fogueira (humana)</column>
			<column name="strTools">1x16+1x7+1x17</column>
			<column name="strConsumed">1x85+1x24</column>
			<column name="strDestroyed"></column>
			<column name="nTreasureID">478</column>
			<column name="fHours">0.25</column>
			<column name="nReverse">0</column>
			<column name="nHiddenID">16</column>
			<column name="bIdentify">0</column>
			<column name="bTransferComponents">0</column>
			<column name="vAlsoTry"></column>
			<column name="nTempTreasureID">3</column>
			<column name="bDegradeOutput">1</column>
			<column name="strType">food</column>
			<column name="bScrap">1</column>
		</table>
		<table name="recipes">
			<column name="nID">73</column>
			<column name="strName">carne assada em um galho (media)</column>
			<column name="strSecretName">carne assada em um galho (media)(humano)</column>
			<column name="strTools">1x7+1x17</column>
			<column name="strConsumed">1x84</column>
			<column name="strDestroyed"></column>
			<column name="nTreasureID">479</column>
			<column name="fHours">0.4</column>
			<column name="nReverse">0</column>
			<column name="nHiddenID">63</column>
			<column name="bIdentify">0</column>
			<column name="bTransferComponents">0</column>
			<column name="vAlsoTry"></column>
			<column name="nTempTreasureID">3</column>
			<column name="bDegradeOutput">1</column>
			<column name="strType">food</column>
			<column name="bScrap">1</column>
		</table>
		<table name="recipes">
			<column name="nID">74</column>
			<column name="strName">carne seca curada sobre fogueira</column>
			<column name="strSecretName">carne seca curada sobre fogueira(humano)</column>
			<column name="strTools">1x16+1x7+1x17</column>
			<column name="strConsumed">1x84+2x24</column>
			<column name="strDestroyed"></column>
			<column name="nTreasureID">480</column>
			<column name="fHours">0.5</column>
			<column name="nReverse">0</column>
			<column name="nHiddenID">64</column>
			<column name="bIdentify">0</column>
			<column name="bTransferComponents">0</column>
			<column name="vAlsoTry"></column>
			<column name="nTempTreasureID">3</column>
			<column name="bDegradeOutput">1</column>
			<column name="strType">food</column>
			<column name="bScrap">1</column>
		</table>
		<table name="recipes">
			<column name="nID">75</column>
			<column name="strName">agua esterilizada (pilula)</column>
			<column name="strSecretName">agua esterilizada (pilula) (veneno)</column>
			<column name="strTools"></column>
			<column name="strConsumed">1x86+1x5</column>
			<column name="strDestroyed"></column>
			<column name="nTreasureID">481</column>
			<column name="fHours">0.1</column>
			<column name="nReverse">0</column>
			<column name="nHiddenID">3</column>
			<column name="bIdentify">0</column>
			<column name="bTransferComponents">0</column>
			<column name="vAlsoTry"></column>
			<column name="nTempTreasureID">3</column>
			<column name="bDegradeOutput">1</column>
			<column name="strType">food</column>
			<column name="bScrap">1</column>
		</table>
		<table name="recipes">
			<column name="nID">76</column>
			<column name="strName">agua esterilizada (cozida)</column>
			<column name="strSecretName">agua esterilizada (fervida) (veneno)</column>
			<column name="strTools">1x6+1x7</column>
			<column name="strConsumed">1x86</column>
			<column name="strDestroyed"></column>
			<column name="nTreasureID">481</column>
			<column name="fHours">0.2</column>
			<column name="nReverse">0</column>
			<column name="nHiddenID">4</column>
			<column name="bIdentify">0</column>
			<column name="bTransferComponents">0</column>
			<column name="vAlsoTry"></column>
			<column name="nTempTreasureID">3</column>
			<column name="bDegradeOutput">1</column>
			<column name="strType">food</column>
			<column name="bScrap">1</column>
		</table>
		<table name="recipes">
			<column name="nID">77</column>
			<column name="strName">agua esterilizada x2 (fervida)</column>
			<column name="strSecretName">agua esterilizada x2 (fervida) (veneno)</column>
			<column name="strTools">1x70+1x7</column>
			<column name="strConsumed">2x86</column>
			<column name="strDestroyed"></column>
			<column name="nTreasureID">483</column>
			<column name="fHours">0.4</column>
			<column name="nReverse">0</column>
			<column name="nHiddenID">56</column>
			<column name="bIdentify">0</column>
			<column name="bTransferComponents">0</column>
			<column name="vAlsoTry"></column>
			<column name="nTempTreasureID">3</column>
			<column name="bDegradeOutput">1</column>
			<column name="strType">food</column>
			<column name="bScrap">1</column>
		</table>
		<table name="recipes">
			<column name="nID">78</column>
			<column name="strName">agua esterilizada x3 (fervida)</column>
			<column name="strSecretName">agua esterilizada x3 (fervida) (veneno)</column>
			<column name="strTools">1x70+1x7</column>
			<column name="strConsumed">3x86</column>
			<column name="strDestroyed"></column>
			<column name="nTreasureID">484</column>
			<column name="fHours">0.6</column>
			<column name="nReverse">0</column>
			<column name="nHiddenID">57</column>
			<column name="bIdentify">0</column>
			<column name="bTransferComponents">0</column>
			<column name="vAlsoTry"></column>
			<column name="nTempTreasureID">3</column>
			<column name="bDegradeOutput">1</column>
			<column name="strType">food</column>
			<column name="bScrap">1</column>
		</table>
		<table name="recipes">
			<column name="nID">79</column>
			<column name="strName">agua analisada</column>
			<column name="strSecretName">agua analisada (veneno)</column>
			<column name="strTools">1x87</column>
			<column name="strConsumed">1x86</column>
			<column name="strDestroyed"></column>
			<column name="nTreasureID">481</column>
			<column name="fHours">0.01</column>
			<column name="nReverse">0</column>
			<column name="nHiddenID">82</column>
			<column name="bIdentify">1</column>
			<column name="bTransferComponents">0</column>
			<column name="vAlsoTry"></column>
			<column name="nTempTreasureID">482</column>
			<column name="bDegradeOutput">1</column>
			<column name="strType">food</column>
			<column name="bScrap">1</column>
		</table>
		<table name="recipes">
			<column name="nID">80</column>
			<column name="strName">agua analisada</column>
			<column name="strSecretName">agua analisada (risco biologico)</column>
			<column name="strTools">1x87</column>
			<column name="strConsumed">1x88</column>
			<column name="strDestroyed"></column>
			<column name="nTreasureID">486</column>
			<column name="fHours">0.01</column>
			<column name="nReverse">0</column>
			<column name="nHiddenID">82</column>
			<column name="bIdentify">1</column>
			<column name="bTransferComponents">0</column>
			<column name="vAlsoTry"></column>
			<column name="nTempTreasureID">482</column>
			<column name="bDegradeOutput">1</column>
			<column name="strType">food</column>
			<column name="bScrap">1</column>
		</table>
		<table name="recipes">
			<column name="nID">81</column>
			<column name="strName">agua analisada</column>
			<column name="strSecretName">agua analisada (nao biologico, nao quimico)</column>
			<column name="strTools">1x87</column>
			<column name="strConsumed">1x89</column>
			<column name="strDestroyed"></column>
			<column name="nTreasureID">20</column>
			<column name="fHours">0.01</column>
			<column name="nReverse">0</column>
			<column name="nHiddenID">82</column>
			<column name="bIdentify">1</column>
			<column name="bTransferComponents">0</column>
			<column name="vAlsoTry"></column>
			<column name="nTempTreasureID">482</column>
			<column name="bDegradeOutput">1</column>
			<column name="strType">food</column>
			<column name="bScrap">1</column>
		</table>
		<table name="recipes">
			<column name="nID">82</column>
			<column name="strName">agua analisada</column>
			<column name="strSecretName">agua analisada (generica)</column>
			<column name="strTools">1x87</column>
			<column name="strConsumed">1x90</column>
			<column name="strDestroyed"></column>
			<column name="nTreasureID">20</column>
			<column name="fHours">0.01</column>
			<column name="nReverse">0</column>
			<column name="nHiddenID">0</column>
			<column name="bIdentify">1</column>
			<column name="bTransferComponents">0</column>
			<column name="vAlsoTry">79,80,81</column>
			<column name="nTempTreasureID">482</column>
			<column name="bDegradeOutput">1</column>
			<column name="strType">food</column>
			<column name="bScrap">1</column>
		</table>
		<table name="recipes">
			<column name="nID">83</column>
			<column name="strName">espingarda (militar) c/alca</column>
			<column name="strSecretName"></column>
			<column name="strTools">1x22</column>
			<column name="strConsumed">1x96+1x18+2x21</column>
			<column name="strDestroyed"></column>
			<column name="nTreasureID">544</column>
			<column name="fHours">0.1</column>
			<column name="nReverse">2</column>
			<column name="nHiddenID">0</column>
			<column name="bIdentify">0</column>
			<column name="bTransferComponents">0</column>
			<column name="vAlsoTry"></column>
			<column name="nTempTreasureID">3</column>
			<column name="bDegradeOutput">1</column>
			<column name="strType">weapon</column>
			<column name="bScrap">1</column>
		</table>
		<table name="recipes">
			<column name="nID">84</column>
			<column name="strName">estilhacos (plastico)</column>
			<column name="strSecretName"></column>
			<column name="strTools"></column>
			<column name="strConsumed">1x97</column>
			<column name="strDestroyed"></column>
			<column name="nTreasureID">601</column>
			<column name="fHours">0.01</column>
			<column name="nReverse">0</column>
			<column name="nHiddenID">0</column>
			<column name="bIdentify">0</column>
			<column name="bTransferComponents">0</column>
			<column name="vAlsoTry"></column>
			<column name="nTempTreasureID">3</column>
			<column name="bDegradeOutput">0</column>
			<column name="strType">misc</column>
			<column name="bScrap">1</column>
		</table>
		<table name="recipes">
			<column name="nID">85</column>
			<column name="strName">4mm Gauss rifle c/luneta/alca</column>
			<column name="strSecretName"></column>
			<column name="strTools">1x22</column>
			<column name="strConsumed">1x100+1x20+1x18+4x21</column>
			<column name="strDestroyed"></column>
			<column name="nTreasureID">673</column>
			<column name="fHours">0.2</column>
			<column name="nReverse">2</column>
			<column name="nHiddenID">0</column>
			<column name="bIdentify">0</column>
			<column name="bTransferComponents">0</column>
			<column name="vAlsoTry"></column>
			<column name="nTempTreasureID">3</column>
			<column name="bDegradeOutput">1</column>
			<column name="strType">weapon</column>
			<column name="bScrap">1</column>
		</table>
		<table name="recipes">
			<column name="nID">86</column>
			<column name="strName">4mm Gauss rifle c/luneta</column>
			<column name="strSecretName"></column>
			<column name="strTools">1x22</column>
			<column name="strConsumed">1x100+1x20+2x21</column>
			<column name="strDestroyed"></column>
			<column name="nTreasureID">671</column>
			<column name="fHours">0.1</column>
			<column name="nReverse">2</column>
			<column name="nHiddenID">0</column>
			<column name="bIdentify">0</column>
			<column name="bTransferComponents">0</column>
			<column name="vAlsoTry"></column>
			<column name="nTempTreasureID">3</column>
			<column name="bDegradeOutput">1</column>
			<column name="strType">weapon</column>
			<column name="bScrap">1</column>
		</table>
		<table name="recipes">
			<column name="nID">87</column>
			<column name="strName">4mm Gauss rifle c/alca</column>
			<column name="strSecretName"></column>
			<column name="strTools">1x22</column>
			<column name="strConsumed">1x100+1x18+2x21</column>
			<column name="strDestroyed"></column>
			<column name="nTreasureID">672</column>
			<column name="fHours">0.1</column>
			<column name="nReverse">2</column>
			<column name="nHiddenID">0</column>
			<column name="bIdentify">0</column>
			<column name="bTransferComponents">0</column>
			<column name="vAlsoTry"></column>
			<column name="nTempTreasureID">3</column>
			<column name="bDegradeOutput">1</column>
			<column name="strType">weapon</column>
			<column name="bScrap">1</column>
		</table>
		<table name="recipes">
			<column name="nID">88</column>
			<column name="strName">4mm Gauss rifle c/luneta, add/alca</column>
			<column name="strSecretName"></column>
			<column name="strTools">1x22</column>
			<column name="strConsumed">1x101+1x18+2x21</column>
			<column name="strDestroyed"></column>
			<column name="nTreasureID">673</column>
			<column name="fHours">0.1</column>
			<column name="nReverse">2</column>
			<column name="nHiddenID">0</column>
			<column name="bIdentify">0</column>
			<column name="bTransferComponents">0</column>
			<column name="vAlsoTry"></column>
			<column name="nTempTreasureID">3</column>
			<column name="bDegradeOutput">1</column>
			<column name="strType">weapon</column>
			<column name="bScrap">1</column>
		</table>
		<table name="recipes">
			<column name="nID">89</column>
			<column name="strName">4mm Gauss rifle c/alca, add/luneta</column>
			<column name="strSecretName"></column>
			<column name="strTools">1x22</column>
			<column name="strConsumed">1x102+1x20+2x21</column>
			<column name="strDestroyed"></column>
			<column name="nTreasureID">673</column>
			<column name="fHours">0.1</column>
			<column name="nReverse">2</column>
			<column name="nHiddenID">0</column>
			<column name="bIdentify">0</column>
			<column name="bTransferComponents">0</column>
			<column name="vAlsoTry"></column>
			<column name="nTempTreasureID">3</column>
			<column name="bDegradeOutput">1</column>
			<column name="strType">weapon</column>
			<column name="bScrap">1</column>
		</table>
		<table name="recipes">
			<column name="nID">90</column>
			<column name="strName">4mm Gauss rifle</column>
			<column name="strSecretName"></column>
			<column name="strTools">1x14+1x22+1x35+1x39+1x40</column>
			<column name="strConsumed">20x21+1x103+3x104+1x105+1x106+1x107+1x108</column>
			<column name="strDestroyed"></column>
			<column name="nTreasureID">674</column>
			<column name="fHours">1</column>
			<column name="nReverse">2</column>
			<column name="nHiddenID">0</column>
			<column name="bIdentify">0</column>
			<column name="bTransferComponents">1</column>
			<column name="vAlsoTry"></column>
			<column name="nTempTreasureID">3</column>
			<column name="bDegradeOutput">1</column>
			<column name="strType">weapon</column>
			<column name="bScrap">1</column>
		</table>
		<table name="recipes">
			<column name="nID">91</column>
			<column name="strName">disabilitado DMC drone wreckage</column>
			<column name="strSecretName"></column>
			<column name="strTools">1x14+1x22+1x40</column>
			<column name="strConsumed">1x109</column>
			<column name="strDestroyed"></column>
			<column name="nTreasureID">675</column>
			<column name="fHours">1</column>
			<column name="nReverse">0</column>
			<column name="nHiddenID">0</column>
			<column name="bIdentify">0</column>
			<column name="bTransferComponents">0</column>
			<column name="vAlsoTry"></column>
			<column name="nTempTreasureID">676</column>
			<column name="bDegradeOutput">1</column>
			<column name="strType">misc</column>
			<column name="bScrap">1</column>
		</table>
		<table name="recipes">
			<column name="nID">92</column>
			<column name="strName">Gauss rifle battery</column>
			<column name="strSecretName"></column>
			<column name="strTools">1x14+1x22+1x39+1x40</column>
			<column name="strConsumed">1x111+12x21</column>
			<column name="strDestroyed"></column>
			<column name="nTreasureID">679</column>
			<column name="fHours">0.5</column>
			<column name="nReverse">0</column>
			<column name="nHiddenID">0</column>
			<column name="bIdentify">0</column>
			<column name="bTransferComponents">0</column>
			<column name="vAlsoTry"></column>
			<column name="nTempTreasureID">3</column>
			<column name="bDegradeOutput">1</column>
			<column name="strType">misc</column>
			<column name="bScrap">1</column>
		</table>
		<table name="recipes">
			<column name="nID">93</column>
			<column name="strName">galho de incenso (aceso)</column>
			<column name="strSecretName"></column>
			<column name="strTools">1x1</column>
			<column name="strConsumed">1x112</column>
			<column name="strDestroyed">2</column>
			<column name="nTreasureID">681</column>
			<column name="fHours">0.1</column>
			<column name="nReverse">0</column>
			<column name="nHiddenID">0</column>
			<column name="bIdentify">0</column>
			<column name="bTransferComponents">0</column>
			<column name="vAlsoTry"></column>
			<column name="nTempTreasureID">3</column>
			<column name="bDegradeOutput">1</column>
			<column name="strType">tool</column>
			<column name="bScrap">1</column>
		</table>
		<table name="recipes">
			<column name="nID">94</column>
			<column name="strName">poncho de retalhos</column>
			<column name="strSecretName"></column>
			<column name="strTools">1x11</column>
			<column name="strConsumed">60x113+20x13</column>
			<column name="strDestroyed"></column>
			<column name="nTreasureID">685</column>
			<column name="fHours">1</column>
			<column name="nReverse">1</column>
			<column name="nHiddenID">0</column>
			<column name="bIdentify">0</column>
			<column name="bTransferComponents">0</column>
			<column name="vAlsoTry"></column>
			<column name="nTempTreasureID">3</column>
			<column name="bDegradeOutput">1</column>
			<column name="strType">misc</column>
			<column name="bScrap">1</column>
		</table>
		<table name="recipes">
			<column name="nID">95</column>
			<column name="strName">restos de folha</column>
			<column name="strSecretName"></column>
			<column name="strTools"></column>
			<column name="strConsumed">1x114</column>
			<column name="strDestroyed"></column>
			<column name="nTreasureID">682</column>
			<column name="fHours">0.01</column>
			<column name="nReverse">0</column>
			<column name="nHiddenID">0</column>
			<column name="bIdentify">0</column>
			<column name="bTransferComponents">0</column>
			<column name="vAlsoTry"></column>
			<column name="nTempTreasureID">3</column>
			<column name="bDegradeOutput">1</column>
			<column name="strType">misc</column>
			<column name="bScrap">1</column>
		</table>
		<table name="recipes">
			<column name="nID">96</column>
			<column name="strName">bermuda</column>
			<column name="strSecretName"></column>
			<column name="strTools">1x14</column>
			<column name="strConsumed">1x118</column>
			<column name="strDestroyed"></column>
			<column name="nTreasureID">743</column>
			<column name="fHours">0.1</column>
			<column name="nReverse">0</column>
			<column name="nHiddenID">0</column>
			<column name="bIdentify">0</column>
			<column name="bTransferComponents">0</column>
			<column name="vAlsoTry"></column>
			<column name="nTempTreasureID">3</column>
			<column name="bDegradeOutput">1</column>
			<column name="strType">misc</column>
			<column name="bScrap">1</column>
		</table>
		<table name="recipes">
			<column name="nID">97</column>
			<column name="strName">bateria pequena "Sparker"</column>
			<column name="strSecretName"></column>
			<column name="strTools"></column>
			<column name="strConsumed">1x119+1x21</column>
			<column name="strDestroyed"></column>
			<column name="nTreasureID">746</column>
			<column name="fHours">0.1</column>
			<column name="nReverse">0</column>
			<column name="nHiddenID">0</column>
			<column name="bIdentify">0</column>
			<column name="bTransferComponents">0</column>
			<column name="vAlsoTry"></column>
			<column name="nTempTreasureID">3</column>
			<column name="bDegradeOutput">1</column>
			<column name="strType">tool</column>
			<column name="bScrap">1</column>
		</table>
		<table name="recipes">
			<column name="nID">98</column>
			<column name="strName">bateria media "Sparker"</column>
			<column name="strSecretName"></column>
			<column name="strTools"></column>
			<column name="strConsumed">1x120+1x21</column>
			<column name="strDestroyed"></column>
			<column name="nTreasureID">747</column>
			<column name="fHours">0.1</column>
			<column name="nReverse">0</column>
			<column name="nHiddenID">0</column>
			<column name="bIdentify">0</column>
			<column name="bTransferComponents">0</column>
			<column name="vAlsoTry"></column>
			<column name="nTempTreasureID">3</column>
			<column name="bDegradeOutput">1</column>
			<column name="strType">tool</column>
			<column name="bScrap">1</column>
		</table>
		<table name="recipes">
			<column name="nID">99</column>
			<column name="strName">pequena fogueira (luz solar focada)</column>
			<column name="strSecretName"></column>
			<column name="strTools">1x121+1x122</column>
			<column name="strConsumed">1x2</column>
			<column name="strDestroyed"></column>
			<column name="nTreasureID">10</column>
			<column name="fHours">0.25</column>
			<column name="nReverse">0</column>
			<column name="nHiddenID">0</column>
			<column name="bIdentify">0</column>
			<column name="bTransferComponents">0</column>
			<column name="vAlsoTry"></column>
			<column name="nTempTreasureID">3</column>
			<column name="bDegradeOutput">0</column>
			<column name="strType">tool</column>
			<column name="bScrap">1</column>
		</table>
		<table name="recipes">
			<column name="nID">100</column>
			<column name="strName">saco improvisado</column>
			<column name="strSecretName"></column>
			<column name="strTools"></column>
			<column name="strConsumed">1x124+1x18</column>
			<column name="strDestroyed"></column>
			<column name="nTreasureID">748</column>
			<column name="fHours">0.1</column>
			<column name="nReverse">0</column>
			<column name="nHiddenID">0</column>
			<column name="bIdentify">0</column>
			<column name="bTransferComponents">1</column>
			<column name="vAlsoTry">101</column>
			<column name="nTempTreasureID">3</column>
			<column name="bDegradeOutput">1</column>
			<column name="strType">tool</column>
			<column name="bScrap">1</column>
		</table>
		<table name="recipes">
			<column name="nID">101</column>
			<column name="strName">saco improvisado (saco de dormir)</column>
			<column name="strSecretName"></column>
			<column name="strTools"></column>
			<column name="strConsumed">1x123</column>
			<column name="strDestroyed"></column>
			<column name="nTreasureID">748</column>
			<column name="fHours">0.1</column>
			<column name="nReverse">0</column>
			<column name="nHiddenID">100</column>
			<column name="bIdentify">0</column>
			<column name="bTransferComponents">1</column>
			<column name="vAlsoTry"></column>
			<column name="nTempTreasureID">3</column>
			<column name="bDegradeOutput">1</column>
			<column name="strType">tool</column>
			<column name="bScrap">1</column>
		</table>
		<table name="recipes">
			<column name="nID">102</column>
			<column name="strName">galho quebrado</column>
			<column name="strSecretName">galho quebrado (somente para reversao)</column>
			<column name="strTools"></column>
			<column name="strConsumed">1x125</column>
			<column name="strDestroyed"></column>
			<column name="nTreasureID">753</column>
			<column name="fHours">0.01</column>
			<column name="nReverse">1</column>
			<column name="nHiddenID">0</column>
			<column name="bIdentify">1</column>
			<column name="bTransferComponents">0</column>
			<column name="vAlsoTry"></column>
			<column name="nTempTreasureID">3</column>
			<column name="bDegradeOutput">1</column>
			<column name="strType">misc</column>
			<column name="bScrap">1</column>
		</table>
		<table name="recipes">
			<column name="nID">103</column>
			<column name="strName">sapato (trapo improvisado)</column>
			<column name="strSecretName"></column>
			<column name="strTools"></column>
			<column name="strConsumed">1x126+4x30</column>
			<column name="strDestroyed"></column>
			<column name="nTreasureID">760</column>
			<column name="fHours">0.25</column>
			<column name="nReverse">1</column>
			<column name="nHiddenID">0</column>
			<column name="bIdentify">0</column>
			<column name="bTransferComponents">0</column>
			<column name="vAlsoTry"></column>
			<column name="nTempTreasureID">3</column>
			<column name="bDegradeOutput">1</column>
			<column name="strType">misc</column>
			<column name="bScrap">1</column>
		</table>
		<table name="recipes">
			<column name="nID">104</column>
			<column name="strName">carne pequena e media em cadaver</column>
			<column name="strSecretName">carne pequena e media em cadaver(animal)</column>
			<column name="strTools">1x14</column>
			<column name="strConsumed">1x127</column>
			<column name="strDestroyed"></column>
			<column name="nTreasureID">762</column>
			<column name="fHours">1</column>
			<column name="nReverse">0</column>
			<column name="nHiddenID">0</column>
			<column name="bIdentify">0</column>
			<column name="bTransferComponents">0</column>
			<column name="vAlsoTry"></column>
			<column name="nTempTreasureID">3</column>
			<column name="bDegradeOutput">1</column>
			<column name="strType">food</column>
			<column name="bScrap">1</column>
		</table>
		<table name="recipes">
			<column name="nID">105</column>
			<column name="strName">carne e couro pequenos e media em cadaver</column>
			<column name="strSecretName">carne e couro pequenos e media em cadaver(animal)</column>
			<column name="strTools">1x14+1x16</column>
			<column name="strConsumed">1x127</column>
			<column name="strDestroyed"></column>
			<column name="nTreasureID">763</column>
			<column name="fHours">1</column>
			<column name="nReverse">0</column>
			<column name="nHiddenID">0</column>
			<column name="bIdentify">0</column>
			<column name="bTransferComponents">0</column>
			<column name="vAlsoTry"></column>
			<column name="nTempTreasureID">3</column>
			<column name="bDegradeOutput">1</column>
			<column name="strType">food</column>
			<column name="bScrap">1</column>
		</table>
	</database>
</pma_xml_export>
